sanzaru/__init__.py
sanzaru/__main__.py
sanzaru/config.py
sanzaru/descriptions.py
sanzaru/exceptions.py
sanzaru/features.py
sanzaru/py.typed
sanzaru/security.py
sanzaru/server.py
sanzaru/types.py
sanzaru/utils.py
sanzaru/audio/__init__.py
sanzaru/audio/config.py
sanzaru/audio/constants.py
sanzaru/audio/file_filter.py
sanzaru/audio/models.py
sanzaru/audio/processor.py
sanzaru/audio/services/__init__.py
sanzaru/audio/services/audio_service.py
sanzaru/audio/services/file_service.py
sanzaru/audio/services/transcription_service.py
sanzaru/audio/services/tts_service.py
sanzaru/infrastructure/__init__.py
sanzaru/infrastructure/cache.py
sanzaru/infrastructure/file_system.py
sanzaru/infrastructure/path_resolver.py
sanzaru/infrastructure/text_utils.py
sanzaru/tools/__init__.py
sanzaru/tools/audio.py
sanzaru/tools/image.py
sanzaru/tools/images_api.py
sanzaru/tools/reference.py
sanzaru/tools/video.py
sanzaru-0.3.2.dist-info/licenses/LICENSE
sanzaru-0.3.2.dist-info/METADATA
sanzaru-0.3.2.dist-info/WHEEL
sanzaru-0.3.2.dist-info/entry_points.txt
sanzaru-0.3.2.dist-info/top_level.txt
sanzaru-0.3.2.dist-info/RECORD
