Metadata-Version: 2.4
Name: sanzaru
Version: 0.3.2
Summary: Unified MCP server for OpenAI multimodal APIs (Sora, Whisper, GPT Vision)
Author-email: Richie Caputo <rcaputo3@tjclp.com>
Maintainer-email: Richie Caputo <rcaputo3@tjclp.com>
License: MIT
Project-URL: Homepage, https://github.com/TJC-LP/sanzaru
Project-URL: Bug Tracker, https://github.com/TJC-LP/sanzaru/issues
Project-URL: Documentation, https://github.com/TJC-LP/sanzaru/tree/main/docs
Project-URL: Source Code, https://github.com/TJC-LP/sanzaru
Keywords: openai,sora,video-generation,mcp,mcp-server,whisper,gpt-4o,audio-transcription,tts,image-generation,ai,multimodal,fastmcp
Classifier: Development Status :: 4 - Beta
Classifier: Intended Audience :: Developers
Classifier: License :: OSI Approved :: MIT License
Classifier: Programming Language :: Python :: 3
Classifier: Programming Language :: Python :: 3.10
Classifier: Programming Language :: Python :: 3.11
Classifier: Programming Language :: Python :: 3.12
Classifier: Programming Language :: Python :: 3.13
Classifier: Programming Language :: Python :: 3.14
Classifier: Topic :: Software Development :: Libraries :: Python Modules
Classifier: Topic :: Multimedia :: Video
Classifier: Topic :: Multimedia :: Sound/Audio
Classifier: Topic :: Scientific/Engineering :: Artificial Intelligence
Classifier: Framework :: FastAPI
Classifier: Operating System :: OS Independent
Requires-Python: >=3.10
License-File: LICENSE
Requires-Dist: openai>=2.13.0
Requires-Dist: mcp>=1.20.0
Requires-Dist: httpx>=0.27.0
Requires-Dist: anyio>=4.0.0
Requires-Dist: aiofiles>=24.0.0
Requires-Dist: pydantic>=2.0.0
Requires-Dist: pydantic-settings>=2.11.0
Provides-Extra: video
Provides-Extra: audio
Requires-Dist: pydub; extra == "audio"
Requires-Dist: ffmpeg-python; extra == "audio"
Requires-Dist: async-lru>=2.0.5; extra == "audio"
Requires-Dist: aioresult>=1.0.0; extra == "audio"
Requires-Dist: audioop-lts; python_version >= "3.13" and extra == "audio"
Provides-Extra: image
Requires-Dist: pillow>=12.0.0; extra == "image"
Provides-Extra: all
Requires-Dist: sanzaru[audio,image,video]; extra == "all"
Dynamic: license-file
